Workbook

Sheet Assumptions
A1: FP&A Financial Forecasting Model — Base Case Assumptions
A2: UK FMCG Cash-and-Carry Distribution Business (illustrative, modeled on Dhamecha Group cost structure)
A4: Assumption | B4: FY2024A | C4: FY2025A | D4: FY2026E | E4: FY2027E | F4: FY2028E
A5: Revenue growth rate (%) | B5: n/a | C5: n/a | D5: 0.07 | E5: 0.09 | F5: 0.08
A6: Cost of sales (% of revenue) | B6: 0.63 | C6: 0.62 | D6: 0.61 | E6: 0.6 | F6: 0.59
A7: SG&A (% of revenue) | B7: 0.17 | C7: 0.16 | D7: 0.155 | E7: 0.15 | F7: 0.145
A8: Tax rate (%) | B8: 0.25 | C8: 0.25 | D8: 0.25 | E8: 0.25 | F8: 0.25
A9: Days Sales Outstanding (AR) | B9: 42 | C9: 40 | D9: 38 | E9: 36 | F9: 35
A10: Days Payable Outstanding (AP) | B10: 58 | C10: 56 | D10: 54 | E10: 52 | F10: 50
A11: Days Inventory (Stock) | B11: 45 | C11: 43 | D11: 41 | E11: 39 | F11: 37
A12: Capex (% of revenue) | B12: 0.03 | C12: 0.03 | D12: 0.03 | E12: 0.03 | F12: 0.03
A13: Depreciation rate (% of opening PP&E) | B13: 0.12 | C13: 0.12 | D13: 0.12 | E13: 0.12 | F13: 0.12
A14: Interest rate on debt (%) | B14: 0.065 | C14: 0.06 | D14: 0.058 | E14: 0.055 | F14: 0.05
A16: Note: Blue = hardcoded assumption inputs. This Base Case feeds the linked 3-statement model below.

Sheet Income Statement
A1: Income Statement (Base Case)
A2: (£ in thousands)
A4: Line Item | B4: FY2024A | C4: FY2025A | D4: FY2026E | E4: FY2027E | F4: FY2028E
A5: Revenue | B5: 11800 | C5: 12850 | D5: =C5*(1+Assumptions!D5) -> 13749.5 | E5: =D5*(1+Assumptions!E5) -> 14986.955 | F5: =E5*(1+Assumptions!F5) -> 16185.911
A6: Cost of Sales | B6: =-B5*Assumptions!B6 -> -7434 | C6: =-C5*Assumptions!C6 -> -7967 | D6: =-D5*Assumptions!D6 -> -8387.195 | E6: =-E5*Assumptions!E6 -> -8992.173 | F6: =-F5*Assumptions!F6 -> -9549.6877
A7: Gross Profit | B7: =B5+B6 -> 4366 | C7: =C5+C6 -> 4883 | D7: =D5+D6 -> 5362.305 | E7: =E5+E6 -> 5994.782 | F7: =F5+F6 -> 6636.2237
A8: Gross Margin % | B8: =B7/B5 -> 0.37 | C8: =C7/C5 -> 0.38 | D8: =D7/D5 -> 0.39 | E8: =E7/E5 -> 0.4 | F8: =F7/F5 -> 0.41
A10: SG&A | B10: =-B5*Assumptions!B7 -> -2006 | C10: =-C5*Assumptions!C7 -> -2056 | D10: =-D5*Assumptions!D7 -> -2131.1725 | E10: =-E5*Assumptions!E7 -> -2248.0433 | F10: =-F5*Assumptions!F7 -> -2346.9572
A11: Depreciation & Amortization | B11: ='Balance Sheet'!B11*Assumptions!B13 -> 732 | C11: ='Balance Sheet'!C11*Assumptions!C13 -> 778.26 | D11: ='Balance Sheet'!D11*Assumptions!D13 -> 827.7582 | E11: ='Balance Sheet'!E11*Assumptions!E13 -> 881.71124 | F11: ='Balance Sheet'!F11*Assumptions!F13 -> 939.98052
A12: EBIT (Operating Income) | B12: =B7+B10-B11 -> 1628 | C12: =C7+C10-C11 -> 2048.74 | D12: =D7+D10-D11 -> 2403.3743 | E12: =E7+E10-E11 -> 2865.0275 | F12: =F7+F10-F11 -> 3349.286
A14: Interest Expense | B14: =-'Balance Sheet'!B18*Assumptions!B14 -> -169 | C14: =-'Balance Sheet'!C18*Assumptions!C14 -> -148.8 | D14: =-'Balance Sheet'!D18*Assumptions!D14 -> -136.88 | E14: =-'Balance Sheet'!E18*Assumptions!E14 -> -123.2 | F14: =-'Balance Sheet'!F18*Assumptions!F14 -> -106
A15: Earnings Before Tax | B15: =B12+B14 -> 1459 | C15: =C12+C14 -> 1899.94 | D15: =D12+D14 -> 2266.4943 | E15: =E12+E14 -> 2741.8275 | F15: =F12+F14 -> 3243.286
A16: Income Tax Expense | B16: =-B15*Assumptions!B8 -> -364.75 | C16: =-C15*Assumptions!C8 -> -474.985 | D16: =-D15*Assumptions!D8 -> -566.62358 | E16: =-E15*Assumptions!E8 -> -685.45688 | F16: =-F15*Assumptions!F8 -> -810.8215
A17: Net Income | B17: =B15+B16 -> 1094.25 | C17: =C15+C16 -> 1424.955 | D17: =D15+D16 -> 1699.8707 | E17: =E15+E16 -> 2056.3706 | F17: =F15+F16 -> 2432.4645
A18: Net Margin % | B18: =B17/B5 -> 0.092733051 | C18: =C17/C5 -> 0.11089144 | D18: =D17/D5 -> 0.12363146 | E18: =E17/E5 -> 0.1372107 | F18: =F17/F5 -> 0.15028283

Sheet Balance Sheet
A1: Balance Sheet (Base Case)
A2: (£ in thousands)
A4: Line Item | B4: FY2024A | C4: FY2025A | D4: FY2026E | E4: FY2027E | F4: FY2028E
A5: ASSETS
A6: Cash & Equivalents | B6: 1650 | C6: =B6+'Cash Flow'!C21 -> 3316.2876 | D6: =C6+'Cash Flow'!D21 -> 5303.1618 | E6: =D6+'Cash Flow'!E21 -> 7646.4715 | F6: =E6+'Cash Flow'!F21 -> 10359.288
A7: Accounts Receivable | B7: ='Income Statement'!B5/365*Assumptions!B9 -> 1357.8082 | C7: ='Income Statement'!C5/365*Assumptions!C9 -> 1408.2192 | D7: ='Income Statement'!D5/365*Assumptions!D9 -> 1431.4548 | E7: ='Income Statement'!E5/365*Assumptions!E9 -> 1478.1654 | F7: ='Income Statement'!F5/365*Assumptions!F9 -> 1552.0737
A8: Inventory (Stock) | B8: =-'Income Statement'!B6/365*Assumptions!B11 -> 916.52055 | C8: =-'Income Statement'!C6/365*Assumptions!C11 -> 938.57808 | D8: =-'Income Statement'!D6/365*Assumptions!D11 -> 942.12327 | E8: =-'Income Statement'!E6/365*Assumptions!E11 -> 960.80753 | F8: =-'Income Statement'!F6/365*Assumptions!F11 -> 968.05054
A9: Total Current Assets | B9: =SUM(B6:B8) -> 3924.3288 | C9: =SUM(C6:C8) -> 5663.0849 | D9: =SUM(D6:D8) -> 7676.7398 | E9: =SUM(E6:E8) -> 10085.444 | F9: =SUM(F6:F8) -> 12879.412
A11: PP&E, Gross | B11: 6100 | C11: =B11+'Cash Flow'!C14*-1 -> 6485.5 | D11: =C11+'Cash Flow'!D14*-1 -> 6897.985 | E11: =D11+'Cash Flow'!E14*-1 -> 7347.5936 | F11: =E11+'Cash Flow'!F14*-1 -> 7833.171
A12: Accumulated Depreciation | B12: -1750 | C12: =B12-'Income Statement'!C11 -> -2528.26 | D12: =C12-'Income Statement'!D11 -> -3356.0182 | E12: =D12-'Income Statement'!E11 -> -4237.7294 | F12: =E12-'Income Statement'!F11 -> -5177.71
A13: PP&E, Net | B13: =B11+B12 -> 4350 | C13: =C11+C12 -> 3957.24 | D13: =D11+D12 -> 3541.9668 | E13: =E11+E12 -> 3109.8642 | F13: =F11+F12 -> 2655.461
A14: TOTAL ASSETS | B14: =B9+B13 -> 8274.3288 | C14: =C9+C13 -> 9620.3249 | D14: =D9+D13 -> 11218.707 | E14: =E9+E13 -> 13195.309 | F14: =F9+F13 -> 15534.873
A16: LIABILITIES & EQUITY
A17: Accounts Payable | B17: =-'Income Statement'!B6/365*Assumptions!B10 -> 1181.2932 | C17: =-'Income Statement'!C6/365*Assumptions!C10 -> 1222.3342 | D17: =-'Income Statement'!D6/365*Assumptions!D10 -> 1240.8453 | E17: =-'Income Statement'!E6/365*Assumptions!E10 -> 1281.0767 | F17: =-'Income Statement'!F6/365*Assumptions!F10 -> 1308.1764
A18: Short-Term Debt / Revolver | B18: 2600 | C18: =B18+'Cash Flow'!C18 -> 2480 | D18: =C18+'Cash Flow'!D18 -> 2360 | E18: =D18+'Cash Flow'!E18 -> 2240 | F18: =E18+'Cash Flow'!F18 -> 2120
A19: Total Current Liabilities | B19: =SUM(B17:B18) -> 3781.2932 | C19: =SUM(C17:C18) -> 3702.3342 | D19: =SUM(D17:D18) -> 3600.8453 | E19: =SUM(E17:E18) -> 3521.0767 | F19: =SUM(F17:F18) -> 3428.1764
A21: Retained Earnings | B21: 3900 | C21: =B21+'Income Statement'!C17 -> 5324.955 | D21: =C21+'Income Statement'!D17 -> 7024.8257 | E21: =D21+'Income Statement'!E17 -> 9081.1964 | F21: =E21+'Income Statement'!F17 -> 11513.661
A22: Common Stock & Paid-in Capital | B22: =B14-B19-B21 -> 593.03562 | C22: =B22 -> 593.03562 | D22: =C22 -> 593.03562 | E22: =D22 -> 593.03562 | F22: =E22 -> 593.03562
A23: Total Equity | B23: =B21+B22 -> 4493.0356 | C23: =C21+C22 -> 5917.9906 | D23: =D21+D22 -> 7617.8613 | E23: =E21+E22 -> 9674.232 | F23: =F21+F22 -> 12106.696
A24: TOTAL LIABILITIES & EQUITY | B24: =B19+B23 -> 8274.3288 | C24: =C19+C23 -> 9620.3249 | D24: =D19+D23 -> 11218.707 | E24: =E19+E23 -> 13195.309 | F24: =F19+F23 -> 15534.873
A26: Balance Check (should be 0) | B26: =B14-B24 -> 0 | C26: =C14-C24 -> 0 | D26: =D14-D24 -> 0 | E26: =E14-E24 -> 0 | F26: =F14-F24 -> 0

Sheet Cash Flow
A1: Cash Flow Statement (Base Case)
A2: (£ in thousands)
A4: Line Item | B4: FY2024A | C4: FY2025A | D4: FY2026E | E4: FY2027E | F4: FY2028E
A5: Operating Activities
A6: Net Income | B6: ='Income Statement'!B17 -> 1094.25 | C6: ='Income Statement'!C17 -> 1424.955 | D6: ='Income Statement'!D17 -> 1699.8707 | E6: ='Income Statement'!E17 -> 2056.3706 | F6: ='Income Statement'!F17 -> 2432.4645
A7: (+) Depreciation & Amortization | B7: ='Income Statement'!B11 -> 732 | C7: ='Income Statement'!C11 -> 778.26 | D7: ='Income Statement'!D11 -> 827.7582 | E7: ='Income Statement'!E11 -> 881.71124 | F7: ='Income Statement'!F11 -> 939.98052
A8: (-) Increase in Accounts Receivable | B8: 0 | C8: =-('Balance Sheet'!C7-'Balance Sheet'!B7) -> -50.410959 | D8: =-('Balance Sheet'!D7-'Balance Sheet'!C7) -> -23.235616 | E8: =-('Balance Sheet'!E7-'Balance Sheet'!D7) -> -46.71063 | F8: =-('Balance Sheet'!F7-'Balance Sheet'!E7) -> -73.908271
A9: (-) Increase in Inventory | B9: 0 | C9: =-('Balance Sheet'!C8-'Balance Sheet'!B8) -> -22.057534 | D9: =-('Balance Sheet'!D8-'Balance Sheet'!C8) -> -3.5451918 | E9: =-('Balance Sheet'!E8-'Balance Sheet'!D8) -> -18.684252 | F9: =-('Balance Sheet'!F8-'Balance Sheet'!E8) -> -7.2430106
A10: (+) Increase in Accounts Payable | B10: 0 | C10: ='Balance Sheet'!C17-'Balance Sheet'!B17 -> 41.041096 | D10: ='Balance Sheet'!D17-'Balance Sheet'!C17 -> 18.511041 | E10: ='Balance Sheet'!E17-'Balance Sheet'!D17 -> 40.231414 | F10: ='Balance Sheet'!F17-'Balance Sheet'!E17 -> 27.099699
A11: Cash Flow from Operations | B11: =SUM(B6:B10) -> 1826.25 | C11: =SUM(C6:C10) -> 2171.7876 | D11: =SUM(D6:D10) -> 2519.3592 | E11: =SUM(E6:E10) -> 2912.9184 | F11: =SUM(F6:F10) -> 3318.3934
A13: Investing Activities
A14: (-) Capital Expenditures | B14: =-'Income Statement'!B5*Assumptions!B12 -> -354 | C14: =-'Income Statement'!C5*Assumptions!C12 -> -385.5 | D14: =-'Income Statement'!D5*Assumptions!D12 -> -412.485 | E14: =-'Income Statement'!E5*Assumptions!E12 -> -449.60865 | F14: =-'Income Statement'!F5*Assumptions!F12 -> -485.57734
A15: Cash Flow from Investing | B15: =B14 -> -354 | C15: =C14 -> -385.5 | D15: =D14 -> -412.485 | E15: =E14 -> -449.60865 | F15: =F14 -> -485.57734
A17: Financing Activities
A18: (+/-) Net Debt Draw / (Repayment) | B18: 0 | C18: -120 | D18: -120 | E18: -120 | F18: -120
A19: Cash Flow from Financing | B19: =B18 -> 0 | C19: =C18 -> -120 | D19: =D18 -> -120 | E19: =E18 -> -120 | F19: =F18 -> -120
A21: Net Change in Cash | B21: 0 | C21: =C11+C15+C19 -> 1666.2876 | D21: =D11+D15+D19 -> 1986.8742 | E21: =E11+E15+E19 -> 2343.3098 | F21: =F11+F15+F19 -> 2712.8161

Sheet Scenario Planning
A1: Scenario Planning — Best / Base / Worst Case
A2: Sensitizing revenue growth and margin assumptions against the Base Case (FY2026E–FY2028E)
A4: Scenario Assumptions
B5: Worst Case | C5: Base Case | D5: Best Case
A6: Avg. annual revenue growth (FY26–FY28) | B6: 0.02 | C6: 0.08 | D6: 0.14
A7: Cost of sales (% of revenue, avg.) | B7: 0.63 | C7: 0.6 | D7: 0.57
A8: SG&A (% of revenue, avg.) | B8: 0.165 | C8: 0.15 | D8: 0.135
A10: Note: Worst/Best cases flex growth ±6pp and margins ±3pp vs Base Case; Base Case values match the linked 3-statement model.
A12: Projected Outputs (FY2028E, cumulative 3-year growth applied to FY2025A base)
B13: Worst Case | C13: Base Case | D13: Best Case
A14: FY2028E Revenue | B14: ='Income Statement'!C5*(1+B6)^3 -> 13636.523 | C14: ='Income Statement'!C5*(1+C6)^3 -> 16187.299 | D14: ='Income Statement'!C5*(1+D6)^3 -> 19037.84
A15: FY2028E Gross Profit | B15: =B14*(1-B7) -> 5045.5134 | C15: =C14*(1-C7) -> 6474.9197 | D15: =D14*(1-D7) -> 8186.2714
A16: FY2028E EBIT (approx.) | B16: =B15-B14*B8 -> 2795.4872 | C16: =C15-C14*C8 -> 4046.8248 | D16: =D15-D14*D8 -> 5616.1629
A17: Implied EBIT Margin % | B17: =B16/B14 -> 0.205 | C17: =C16/C14 -> 0.25 | D17: =D16/D14 -> 0.295
A18: FY2028E Net Income (approx., 25% tax) | B18: =B16*0.75 -> 2096.6154 | C18: =C16*0.75 -> 3035.1186 | D18: =D16*0.75 -> 4212.1222
A19: Net Income vs. Base Case | B19: =B18/$C$18-1 -> -0.30921468 | C19: =C18/$C$18-1 -> 0 | D19: =D18/$C$18-1 -> 0.38779492

Sheet Revenue Forecast
A1: Revenue Forecast — Historical + Scenario Projections
A2: (£ in thousands)
A4: Year | B4: Actual/Base | C4: Worst Case | D4: Best Case
A5: FY2024A | B5: ='Income Statement'!B5 -> 11800
A6: FY2025A | B6: ='Income Statement'!C5 -> 12850
A7: FY2026E | B7: ='Income Statement'!D5 -> 13749.5 | C7: ='Income Statement'!C5*(1+'Scenario Planning'!$B$6)^1 -> 13107 | D7: ='Income Statement'!C5*(1+'Scenario Planning'!$D$6)^1 -> 14649
A8: FY2027E | B8: ='Income Statement'!E5 -> 14986.955 | C8: ='Income Statement'!C5*(1+'Scenario Planning'!$B$6)^2 -> 13369.14 | D8: ='Income Statement'!C5*(1+'Scenario Planning'!$D$6)^2 -> 16699.86
A9: FY2028E | B9: ='Income Statement'!F5 -> 16185.911 | C9: ='Income Statement'!C5*(1+'Scenario Planning'!$B$6)^3 -> 13636.523 | D9: ='Income Statement'!C5*(1+'Scenario Planning'!$D$6)^3 -> 19037.84
