Workbook

Sheet Dashboard
B2: BUDGET vs ACTUAL FP&A DASHBOARD
B3: Monthly Variance Analysis | Revenue & Expense Tracking | Forecast Accuracy — Rajnandan Basu
B5: Month Filter | C5: All | H5: MonthCrit | I5: =IF(C5="All","*",C5) -> *
B6: Select a month above, or "All" for full-period totals — KPIs update automatically.
B8: Revenue: Budget | E8: Revenue: Actual | H8: Revenue Variance % | K8: Forecast Accuracy % (Full Period)
B9: =SUMIFS(Data!$E:$E,Data!$A:$A,$I$5,Data!$C:$C,"Revenue") -> 29478828 | E9: =SUMIFS(Data!$F:$F,Data!$A:$A,$I$5,Data!$C:$C,"Revenue") -> 29485309 | H9: =IFERROR((E9-B9)/B9,0) -> 0.0002198527 | K9: =1-SUMPRODUCT(ABS(Data!$G$2:$G$217-Data!$F$2:$F$217)*(Data!$C$2:$C$217="Revenue"))/SUMIFS(Data!$F:$F,Data!$C:$C,"Revenue") -> 0.96051356
B11: Expense: Budget | E11: Expense: Actual | H11: Expense Variance % | K11: Net Variance (£)
B12: =SUMIFS(Data!$E:$E,Data!$A:$A,$I$5,Data!$C:$C,"Expense") -> 28325307 | E12: =SUMIFS(Data!$F:$F,Data!$A:$A,$I$5,Data!$C:$C,"Expense") -> 28302005 | H12: =IFERROR((E12-B12)/B12,0) -> -0.00082265657 | K12: =(E9-B9)-(E12-B12) -> 29783
B15: MONTHLY REVENUE: BUDGET vs ACTUAL
B16: Month | C16: Budget | D16: Actual
B17: Jan-25 | C17: =SUMIFS(Data!$E:$E,Data!$A:$A,"Jan-25",Data!$C:$C,"Revenue") -> 1177188 | D17: =SUMIFS(Data!$F:$F,Data!$A:$A,"Jan-25",Data!$C:$C,"Revenue") -> 1208440
B18: Feb-25 | C18: =SUMIFS(Data!$E:$E,Data!$A:$A,"Feb-25",Data!$C:$C,"Revenue") -> 1224796 | D18: =SUMIFS(Data!$F:$F,Data!$A:$A,"Feb-25",Data!$C:$C,"Revenue") -> 1131243
B19: Mar-25 | C19: =SUMIFS(Data!$E:$E,Data!$A:$A,"Mar-25",Data!$C:$C,"Revenue") -> 1254585 | D19: =SUMIFS(Data!$F:$F,Data!$A:$A,"Mar-25",Data!$C:$C,"Revenue") -> 1259931
B20: Apr-25 | C20: =SUMIFS(Data!$E:$E,Data!$A:$A,"Apr-25",Data!$C:$C,"Revenue") -> 1260173 | D20: =SUMIFS(Data!$F:$F,Data!$A:$A,"Apr-25",Data!$C:$C,"Revenue") -> 1213401
B21: May-25 | C21: =SUMIFS(Data!$E:$E,Data!$A:$A,"May-25",Data!$C:$C,"Revenue") -> 1241622 | D21: =SUMIFS(Data!$F:$F,Data!$A:$A,"May-25",Data!$C:$C,"Revenue") -> 1239122
B22: Jun-25 | C22: =SUMIFS(Data!$E:$E,Data!$A:$A,"Jun-25",Data!$C:$C,"Revenue") -> 1205512 | D22: =SUMIFS(Data!$F:$F,Data!$A:$A,"Jun-25",Data!$C:$C,"Revenue") -> 1188400
B23: Jul-25 | C23: =SUMIFS(Data!$E:$E,Data!$A:$A,"Jul-25",Data!$C:$C,"Revenue") -> 1163233 | D23: =SUMIFS(Data!$F:$F,Data!$A:$A,"Jul-25",Data!$C:$C,"Revenue") -> 1094606
B24: Aug-25 | C24: =SUMIFS(Data!$E:$E,Data!$A:$A,"Aug-25",Data!$C:$C,"Revenue") -> 1127975 | D24: =SUMIFS(Data!$F:$F,Data!$A:$A,"Aug-25",Data!$C:$C,"Revenue") -> 1037319
B25: Sep-25 | C25: =SUMIFS(Data!$E:$E,Data!$A:$A,"Sep-25",Data!$C:$C,"Revenue") -> 1111185 | D25: =SUMIFS(Data!$F:$F,Data!$A:$A,"Sep-25",Data!$C:$C,"Revenue") -> 1151756
B26: Oct-25 | C26: =SUMIFS(Data!$E:$E,Data!$A:$A,"Oct-25",Data!$C:$C,"Revenue") -> 1119463 | D26: =SUMIFS(Data!$F:$F,Data!$A:$A,"Oct-25",Data!$C:$C,"Revenue") -> 1084481
B27: Nov-25 | C27: =SUMIFS(Data!$E:$E,Data!$A:$A,"Nov-25",Data!$C:$C,"Revenue") -> 1152727 | D27: =SUMIFS(Data!$F:$F,Data!$A:$A,"Nov-25",Data!$C:$C,"Revenue") -> 1111088
B28: Dec-25 | C28: =SUMIFS(Data!$E:$E,Data!$A:$A,"Dec-25",Data!$C:$C,"Revenue") -> 1204154 | D28: =SUMIFS(Data!$F:$F,Data!$A:$A,"Dec-25",Data!$C:$C,"Revenue") -> 1296100
B29: Jan-26 | C29: =SUMIFS(Data!$E:$E,Data!$A:$A,"Jan-26",Data!$C:$C,"Revenue") -> 1261945 | D29: =SUMIFS(Data!$F:$F,Data!$A:$A,"Jan-26",Data!$C:$C,"Revenue") -> 1291383
B30: Feb-26 | C30: =SUMIFS(Data!$E:$E,Data!$A:$A,"Feb-26",Data!$C:$C,"Revenue") -> 1312455 | D30: =SUMIFS(Data!$F:$F,Data!$A:$A,"Feb-26",Data!$C:$C,"Revenue") -> 1379903
B31: Mar-26 | C31: =SUMIFS(Data!$E:$E,Data!$A:$A,"Mar-26",Data!$C:$C,"Revenue") -> 1343846 | D31: =SUMIFS(Data!$F:$F,Data!$A:$A,"Mar-26",Data!$C:$C,"Revenue") -> 1326208
B32: Apr-26 | C32: =SUMIFS(Data!$E:$E,Data!$A:$A,"Apr-26",Data!$C:$C,"Revenue") -> 1349302 | D32: =SUMIFS(Data!$F:$F,Data!$A:$A,"Apr-26",Data!$C:$C,"Revenue") -> 1437707
B33: May-26 | C33: =SUMIFS(Data!$E:$E,Data!$A:$A,"May-26",Data!$C:$C,"Revenue") -> 1328924 | D33: =SUMIFS(Data!$F:$F,Data!$A:$A,"May-26",Data!$C:$C,"Revenue") -> 1292078
B34: Jun-26 | C34: =SUMIFS(Data!$E:$E,Data!$A:$A,"Jun-26",Data!$C:$C,"Revenue") -> 1289781 | D34: =SUMIFS(Data!$F:$F,Data!$A:$A,"Jun-26",Data!$C:$C,"Revenue") -> 1310101
B35: Jul-26 | C35: =SUMIFS(Data!$E:$E,Data!$A:$A,"Jul-26",Data!$C:$C,"Revenue") -> 1244076 | D35: =SUMIFS(Data!$F:$F,Data!$A:$A,"Jul-26",Data!$C:$C,"Revenue") -> 1279890
B36: Aug-26 | C36: =SUMIFS(Data!$E:$E,Data!$A:$A,"Aug-26",Data!$C:$C,"Revenue") -> 1205916 | D36: =SUMIFS(Data!$F:$F,Data!$A:$A,"Aug-26",Data!$C:$C,"Revenue") -> 1250876
B37: Sep-26 | C37: =SUMIFS(Data!$E:$E,Data!$A:$A,"Sep-26",Data!$C:$C,"Revenue") -> 1187525 | D37: =SUMIFS(Data!$F:$F,Data!$A:$A,"Sep-26",Data!$C:$C,"Revenue") -> 1096363
B38: Oct-26 | C38: =SUMIFS(Data!$E:$E,Data!$A:$A,"Oct-26",Data!$C:$C,"Revenue") -> 1195935 | D38: =SUMIFS(Data!$F:$F,Data!$A:$A,"Oct-26",Data!$C:$C,"Revenue") -> 1208719
B39: Nov-26 | C39: =SUMIFS(Data!$E:$E,Data!$A:$A,"Nov-26",Data!$C:$C,"Revenue") -> 1231025 | D39: =SUMIFS(Data!$F:$F,Data!$A:$A,"Nov-26",Data!$C:$C,"Revenue") -> 1311042
B40: Dec-26 | C40: =SUMIFS(Data!$E:$E,Data!$A:$A,"Dec-26",Data!$C:$C,"Revenue") -> 1285485 | D40: =SUMIFS(Data!$F:$F,Data!$A:$A,"Dec-26",Data!$C:$C,"Revenue") -> 1285152
B43: MONTHLY EXPENSE: BUDGET vs ACTUAL
B44: Month | C44: Budget | D44: Actual
B45: Jan-25 | C45: =SUMIFS(Data!$E:$E,Data!$A:$A,"Jan-25",Data!$C:$C,"Expense") -> 1131124 | D45: =SUMIFS(Data!$F:$F,Data!$A:$A,"Jan-25",Data!$C:$C,"Expense") -> 1178140
B46: Feb-25 | C46: =SUMIFS(Data!$E:$E,Data!$A:$A,"Feb-25",Data!$C:$C,"Expense") -> 1176870 | D46: =SUMIFS(Data!$F:$F,Data!$A:$A,"Feb-25",Data!$C:$C,"Expense") -> 1196035
B47: Mar-25 | C47: =SUMIFS(Data!$E:$E,Data!$A:$A,"Mar-25",Data!$C:$C,"Expense") -> 1205494 | D47: =SUMIFS(Data!$F:$F,Data!$A:$A,"Mar-25",Data!$C:$C,"Expense") -> 1242149
B48: Apr-25 | C48: =SUMIFS(Data!$E:$E,Data!$A:$A,"Apr-25",Data!$C:$C,"Expense") -> 1210862 | D48: =SUMIFS(Data!$F:$F,Data!$A:$A,"Apr-25",Data!$C:$C,"Expense") -> 1192454
B49: May-25 | C49: =SUMIFS(Data!$E:$E,Data!$A:$A,"May-25",Data!$C:$C,"Expense") -> 1193038 | D49: =SUMIFS(Data!$F:$F,Data!$A:$A,"May-25",Data!$C:$C,"Expense") -> 1208683
B50: Jun-25 | C50: =SUMIFS(Data!$E:$E,Data!$A:$A,"Jun-25",Data!$C:$C,"Expense") -> 1158340 | D50: =SUMIFS(Data!$F:$F,Data!$A:$A,"Jun-25",Data!$C:$C,"Expense") -> 1089801
B51: Jul-25 | C51: =SUMIFS(Data!$E:$E,Data!$A:$A,"Jul-25",Data!$C:$C,"Expense") -> 1117716 | D51: =SUMIFS(Data!$F:$F,Data!$A:$A,"Jul-25",Data!$C:$C,"Expense") -> 1069997
B52: Aug-25 | C52: =SUMIFS(Data!$E:$E,Data!$A:$A,"Aug-25",Data!$C:$C,"Expense") -> 1083837 | D52: =SUMIFS(Data!$F:$F,Data!$A:$A,"Aug-25",Data!$C:$C,"Expense") -> 1118043
B53: Sep-25 | C53: =SUMIFS(Data!$E:$E,Data!$A:$A,"Sep-25",Data!$C:$C,"Expense") -> 1067703 | D53: =SUMIFS(Data!$F:$F,Data!$A:$A,"Sep-25",Data!$C:$C,"Expense") -> 1144099
B54: Oct-25 | C54: =SUMIFS(Data!$E:$E,Data!$A:$A,"Oct-25",Data!$C:$C,"Expense") -> 1075658 | D54: =SUMIFS(Data!$F:$F,Data!$A:$A,"Oct-25",Data!$C:$C,"Expense") -> 1074619
B55: Nov-25 | C55: =SUMIFS(Data!$E:$E,Data!$A:$A,"Nov-25",Data!$C:$C,"Expense") -> 1107619 | D55: =SUMIFS(Data!$F:$F,Data!$A:$A,"Nov-25",Data!$C:$C,"Expense") -> 1086275
B56: Dec-25 | C56: =SUMIFS(Data!$E:$E,Data!$A:$A,"Dec-25",Data!$C:$C,"Expense") -> 1157035 | D56: =SUMIFS(Data!$F:$F,Data!$A:$A,"Dec-25",Data!$C:$C,"Expense") -> 1191565
B57: Jan-26 | C57: =SUMIFS(Data!$E:$E,Data!$A:$A,"Jan-26",Data!$C:$C,"Expense") -> 1212565 | D57: =SUMIFS(Data!$F:$F,Data!$A:$A,"Jan-26",Data!$C:$C,"Expense") -> 1199969
B58: Feb-26 | C58: =SUMIFS(Data!$E:$E,Data!$A:$A,"Feb-26",Data!$C:$C,"Expense") -> 1261098 | D58: =SUMIFS(Data!$F:$F,Data!$A:$A,"Feb-26",Data!$C:$C,"Expense") -> 1261915
B59: Mar-26 | C59: =SUMIFS(Data!$E:$E,Data!$A:$A,"Mar-26",Data!$C:$C,"Expense") -> 1291260 | D59: =SUMIFS(Data!$F:$F,Data!$A:$A,"Mar-26",Data!$C:$C,"Expense") -> 1232050
B60: Apr-26 | C60: =SUMIFS(Data!$E:$E,Data!$A:$A,"Apr-26",Data!$C:$C,"Expense") -> 1296502 | D60: =SUMIFS(Data!$F:$F,Data!$A:$A,"Apr-26",Data!$C:$C,"Expense") -> 1261160
B61: May-26 | C61: =SUMIFS(Data!$E:$E,Data!$A:$A,"May-26",Data!$C:$C,"Expense") -> 1276923 | D61: =SUMIFS(Data!$F:$F,Data!$A:$A,"May-26",Data!$C:$C,"Expense") -> 1327237
B62: Jun-26 | C62: =SUMIFS(Data!$E:$E,Data!$A:$A,"Jun-26",Data!$C:$C,"Expense") -> 1239312 | D62: =SUMIFS(Data!$F:$F,Data!$A:$A,"Jun-26",Data!$C:$C,"Expense") -> 1207249
B63: Jul-26 | C63: =SUMIFS(Data!$E:$E,Data!$A:$A,"Jul-26",Data!$C:$C,"Expense") -> 1195393 | D63: =SUMIFS(Data!$F:$F,Data!$A:$A,"Jul-26",Data!$C:$C,"Expense") -> 1226762
B64: Aug-26 | C64: =SUMIFS(Data!$E:$E,Data!$A:$A,"Aug-26",Data!$C:$C,"Expense") -> 1158726 | D64: =SUMIFS(Data!$F:$F,Data!$A:$A,"Aug-26",Data!$C:$C,"Expense") -> 1110361
B65: Sep-26 | C65: =SUMIFS(Data!$E:$E,Data!$A:$A,"Sep-26",Data!$C:$C,"Expense") -> 1141057 | D65: =SUMIFS(Data!$F:$F,Data!$A:$A,"Sep-26",Data!$C:$C,"Expense") -> 1088044
B66: Oct-26 | C66: =SUMIFS(Data!$E:$E,Data!$A:$A,"Oct-26",Data!$C:$C,"Expense") -> 1149137 | D66: =SUMIFS(Data!$F:$F,Data!$A:$A,"Oct-26",Data!$C:$C,"Expense") -> 1210982
B67: Nov-26 | C67: =SUMIFS(Data!$E:$E,Data!$A:$A,"Nov-26",Data!$C:$C,"Expense") -> 1182855 | D67: =SUMIFS(Data!$F:$F,Data!$A:$A,"Nov-26",Data!$C:$C,"Expense") -> 1118261
B68: Dec-26 | C68: =SUMIFS(Data!$E:$E,Data!$A:$A,"Dec-26",Data!$C:$C,"Expense") -> 1235183 | D68: =SUMIFS(Data!$F:$F,Data!$A:$A,"Dec-26",Data!$C:$C,"Expense") -> 1266155
B71: FORECAST ACCURACY TRACKING (Revenue, by month)
B72: Month | C72: Forecast | D72: Actual | E72: Accuracy %
B73: Jan-25 | C73: =SUMIFS(Data!$G:$G,Data!$A:$A,"Jan-25",Data!$C:$C,"Revenue") -> 1167208 | D73: =SUMIFS(Data!$F:$F,Data!$A:$A,"Jan-25",Data!$C:$C,"Revenue") -> 1208440 | E73: =1-ABS(D73-C73)/D73 -> 0.96587998
B74: Feb-25 | C74: =SUMIFS(Data!$G:$G,Data!$A:$A,"Feb-25",Data!$C:$C,"Revenue") -> 1100603 | D74: =SUMIFS(Data!$F:$F,Data!$A:$A,"Feb-25",Data!$C:$C,"Revenue") -> 1131243 | E74: =1-ABS(D74-C74)/D74 -> 0.97291475
B75: Mar-25 | C75: =SUMIFS(Data!$G:$G,Data!$A:$A,"Mar-25",Data!$C:$C,"Revenue") -> 1300553 | D75: =SUMIFS(Data!$F:$F,Data!$A:$A,"Mar-25",Data!$C:$C,"Revenue") -> 1259931 | E75: =1-ABS(D75-C75)/D75 -> 0.96775855
B76: Apr-25 | C76: =SUMIFS(Data!$G:$G,Data!$A:$A,"Apr-25",Data!$C:$C,"Revenue") -> 1273077 | D76: =SUMIFS(Data!$F:$F,Data!$A:$A,"Apr-25",Data!$C:$C,"Revenue") -> 1213401 | E76: =1-ABS(D76-C76)/D76 -> 0.95081923
B77: May-25 | C77: =SUMIFS(Data!$G:$G,Data!$A:$A,"May-25",Data!$C:$C,"Revenue") -> 1277127 | D77: =SUMIFS(Data!$F:$F,Data!$A:$A,"May-25",Data!$C:$C,"Revenue") -> 1239122 | E77: =1-ABS(D77-C77)/D77 -> 0.96932909
B78: Jun-25 | C78: =SUMIFS(Data!$G:$G,Data!$A:$A,"Jun-25",Data!$C:$C,"Revenue") -> 1210014 | D78: =SUMIFS(Data!$F:$F,Data!$A:$A,"Jun-25",Data!$C:$C,"Revenue") -> 1188400 | E78: =1-ABS(D78-C78)/D78 -> 0.98181252
B79: Jul-25 | C79: =SUMIFS(Data!$G:$G,Data!$A:$A,"Jul-25",Data!$C:$C,"Revenue") -> 1065288 | D79: =SUMIFS(Data!$F:$F,Data!$A:$A,"Jul-25",Data!$C:$C,"Revenue") -> 1094606 | E79: =1-ABS(D79-C79)/D79 -> 0.97321593
B80: Aug-25 | C80: =SUMIFS(Data!$G:$G,Data!$A:$A,"Aug-25",Data!$C:$C,"Revenue") -> 1046842 | D80: =SUMIFS(Data!$F:$F,Data!$A:$A,"Aug-25",Data!$C:$C,"Revenue") -> 1037319 | E80: =1-ABS(D80-C80)/D80 -> 0.9908196
B81: Sep-25 | C81: =SUMIFS(Data!$G:$G,Data!$A:$A,"Sep-25",Data!$C:$C,"Revenue") -> 1141523 | D81: =SUMIFS(Data!$F:$F,Data!$A:$A,"Sep-25",Data!$C:$C,"Revenue") -> 1151756 | E81: =1-ABS(D81-C81)/D81 -> 0.99111531
B82: Oct-25 | C82: =SUMIFS(Data!$G:$G,Data!$A:$A,"Oct-25",Data!$C:$C,"Revenue") -> 1110061 | D82: =SUMIFS(Data!$F:$F,Data!$A:$A,"Oct-25",Data!$C:$C,"Revenue") -> 1084481 | E82: =1-ABS(D82-C82)/D82 -> 0.97641268
B83: Nov-25 | C83: =SUMIFS(Data!$G:$G,Data!$A:$A,"Nov-25",Data!$C:$C,"Revenue") -> 1113589 | D83: =SUMIFS(Data!$F:$F,Data!$A:$A,"Nov-25",Data!$C:$C,"Revenue") -> 1111088 | E83: =1-ABS(D83-C83)/D83 -> 0.99774905
B84: Dec-25 | C84: =SUMIFS(Data!$G:$G,Data!$A:$A,"Dec-25",Data!$C:$C,"Revenue") -> 1282779 | D84: =SUMIFS(Data!$F:$F,Data!$A:$A,"Dec-25",Data!$C:$C,"Revenue") -> 1296100 | E84: =1-ABS(D84-C84)/D84 -> 0.98972224
B85: Jan-26 | C85: =SUMIFS(Data!$G:$G,Data!$A:$A,"Jan-26",Data!$C:$C,"Revenue") -> 1259009 | D85: =SUMIFS(Data!$F:$F,Data!$A:$A,"Jan-26",Data!$C:$C,"Revenue") -> 1291383 | E85: =1-ABS(D85-C85)/D85 -> 0.97493075
B86: Feb-26 | C86: =SUMIFS(Data!$G:$G,Data!$A:$A,"Feb-26",Data!$C:$C,"Revenue") -> 1339825 | D86: =SUMIFS(Data!$F:$F,Data!$A:$A,"Feb-26",Data!$C:$C,"Revenue") -> 1379903 | E86: =1-ABS(D86-C86)/D86 -> 0.97095593
B87: Mar-26 | C87: =SUMIFS(Data!$G:$G,Data!$A:$A,"Mar-26",Data!$C:$C,"Revenue") -> 1340605 | D87: =SUMIFS(Data!$F:$F,Data!$A:$A,"Mar-26",Data!$C:$C,"Revenue") -> 1326208 | E87: =1-ABS(D87-C87)/D87 -> 0.98914424
B88: Apr-26 | C88: =SUMIFS(Data!$G:$G,Data!$A:$A,"Apr-26",Data!$C:$C,"Revenue") -> 1395967 | D88: =SUMIFS(Data!$F:$F,Data!$A:$A,"Apr-26",Data!$C:$C,"Revenue") -> 1437707 | E88: =1-ABS(D88-C88)/D88 -> 0.97096766
B89: May-26 | C89: =SUMIFS(Data!$G:$G,Data!$A:$A,"May-26",Data!$C:$C,"Revenue") -> 1277414 | D89: =SUMIFS(Data!$F:$F,Data!$A:$A,"May-26",Data!$C:$C,"Revenue") -> 1292078 | E89: =1-ABS(D89-C89)/D89 -> 0.98865084
B90: Jun-26 | C90: =SUMIFS(Data!$G:$G,Data!$A:$A,"Jun-26",Data!$C:$C,"Revenue") -> 1318244 | D90: =SUMIFS(Data!$F:$F,Data!$A:$A,"Jun-26",Data!$C:$C,"Revenue") -> 1310101 | E90: =1-ABS(D90-C90)/D90 -> 0.99378445
B91: Jul-26 | C91: =SUMIFS(Data!$G:$G,Data!$A:$A,"Jul-26",Data!$C:$C,"Revenue") -> 1347386 | D91: =SUMIFS(Data!$F:$F,Data!$A:$A,"Jul-26",Data!$C:$C,"Revenue") -> 1279890 | E91: =1-ABS(D91-C91)/D91 -> 0.94726422
B92: Aug-26 | C92: =SUMIFS(Data!$G:$G,Data!$A:$A,"Aug-26",Data!$C:$C,"Revenue") -> 1245053 | D92: =SUMIFS(Data!$F:$F,Data!$A:$A,"Aug-26",Data!$C:$C,"Revenue") -> 1250876 | E92: =1-ABS(D92-C92)/D92 -> 0.99534486
B93: Sep-26 | C93: =SUMIFS(Data!$G:$G,Data!$A:$A,"Sep-26",Data!$C:$C,"Revenue") -> 1109056 | D93: =SUMIFS(Data!$F:$F,Data!$A:$A,"Sep-26",Data!$C:$C,"Revenue") -> 1096363 | E93: =1-ABS(D93-C93)/D93 -> 0.98842263
B94: Oct-26 | C94: =SUMIFS(Data!$G:$G,Data!$A:$A,"Oct-26",Data!$C:$C,"Revenue") -> 1174899 | D94: =SUMIFS(Data!$F:$F,Data!$A:$A,"Oct-26",Data!$C:$C,"Revenue") -> 1208719 | E94: =1-ABS(D94-C94)/D94 -> 0.97201996
B95: Nov-26 | C95: =SUMIFS(Data!$G:$G,Data!$A:$A,"Nov-26",Data!$C:$C,"Revenue") -> 1324499 | D95: =SUMIFS(Data!$F:$F,Data!$A:$A,"Nov-26",Data!$C:$C,"Revenue") -> 1311042 | E95: =1-ABS(D95-C95)/D95 -> 0.98973565
B96: Dec-26 | C96: =SUMIFS(Data!$G:$G,Data!$A:$A,"Dec-26",Data!$C:$C,"Revenue") -> 1337048 | D96: =SUMIFS(Data!$F:$F,Data!$A:$A,"Dec-26",Data!$C:$C,"Revenue") -> 1285152 | E96: =1-ABS(D96-C96)/D96 -> 0.95961878
B99: VARIANCE BY CATEGORY (Full Period)
B100: Category | C100: Type | D100: Budget | E100: Actual | F100: Variance %
B101: Retail Sales | C101: Revenue | D101: =SUMIFS(Data!$E:$E,Data!$D:$D,"Retail Sales") -> 12304203 | E101: =SUMIFS(Data!$F:$F,Data!$D:$D,"Retail Sales") -> 12171664 | F101: =(E101-D101)/D101 -> -0.010771848
B102: Wholesale | C102: Revenue | D102: =SUMIFS(Data!$E:$E,Data!$D:$D,"Wholesale") -> 8202806 | E102: =SUMIFS(Data!$F:$F,Data!$D:$D,"Wholesale") -> 8252475 | F102: =(E102-D102)/D102 -> 0.0060551231
B103: Online Sales | C103: Revenue | D103: =SUMIFS(Data!$E:$E,Data!$D:$D,"Online Sales") -> 5383091 | E103: =SUMIFS(Data!$F:$F,Data!$D:$D,"Online Sales") -> 5429259 | F103: =(E103-D103)/D103 -> 0.0085764851
B104: Foodservice | C104: Revenue | D104: =SUMIFS(Data!$E:$E,Data!$D:$D,"Foodservice") -> 3588728 | E104: =SUMIFS(Data!$F:$F,Data!$D:$D,"Foodservice") -> 3631911 | F104: =(E104-D104)/D104 -> 0.012032954
B105: Cost of Goods Sold | C105: Expense | D105: =SUMIFS(Data!$E:$E,Data!$D:$D,"Cost of Goods Sold") -> 16661944 | E105: =SUMIFS(Data!$F:$F,Data!$D:$D,"Cost of Goods Sold") -> 16675186 | F105: =(E105-D105)/D105 -> 0.0007947452
B106: Payroll | C106: Expense | D106: =SUMIFS(Data!$E:$E,Data!$D:$D,"Payroll") -> 6152104 | E106: =SUMIFS(Data!$F:$F,Data!$D:$D,"Payroll") -> 6124732 | F106: =(E106-D106)/D106 -> -0.0044492096
B107: Marketing | C107: Expense | D107: =SUMIFS(Data!$E:$E,Data!$D:$D,"Marketing") -> 1666194 | E107: =SUMIFS(Data!$F:$F,Data!$D:$D,"Marketing") -> 1675875 | F107: =(E107-D107)/D107 -> 0.0058102478
B108: Logistics & Distribution | C108: Expense | D108: =SUMIFS(Data!$E:$E,Data!$D:$D,"Logistics & Distribution") -> 2435207 | E108: =SUMIFS(Data!$F:$F,Data!$D:$D,"Logistics & Distribution") -> 2429586 | F108: =(E108-D108)/D108 -> -0.0023082227
B109: Admin & Overheads | C109: Expense | D109: =SUMIFS(Data!$E:$E,Data!$D:$D,"Admin & Overheads") -> 1409858 | E109: =SUMIFS(Data!$F:$F,Data!$D:$D,"Admin & Overheads") -> 1396626 | F109: =(E109-D109)/D109 -> -0.0093853424

Sheet Data
A1: Month | B1: MonthIndex | C1: Type | D1: Category | E1: Budget | F1: Actual | G1: Forecast
A2: Jan-25 | B2: 1 | C2: Revenue | D2: Retail Sales | E2: 491348 | F2: 489561 | G2: 487111
A3: Jan-25 | B3: 1 | C3: Revenue | D3: Wholesale | E3: 327565 | F3: 351453 | G3: 331577
A4: Jan-25 | B4: 1 | C4: Revenue | D4: Online Sales | E4: 214965 | F4: 226181 | G4: 208766
A5: Jan-25 | B5: 1 | C5: Revenue | D5: Foodservice | E5: 143310 | F5: 141245 | G5: 139754
A6: Jan-25 | B6: 1 | C6: Expense | D6: Cost of Goods Sold | E6: 665367 | F6: 710405 | G6: 710046
A7: Jan-25 | B7: 1 | C7: Expense | D7: Payroll | E7: 245674 | F7: 236635 | G7: 249638
A8: Jan-25 | B8: 1 | C8: Expense | D8: Marketing | E8: 66537 | F8: 72968 | G8: 70956
A9: Jan-25 | B9: 1 | C9: Expense | D9: Logistics & Distribution | E9: 97246 | F9: 101283 | G9: 99468
A10: Jan-25 | B10: 1 | C10: Expense | D10: Admin & Overheads | E10: 56300 | F10: 56849 | G10: 57434
A11: Feb-25 | B11: 2 | C11: Revenue | D11: Retail Sales | E11: 511219 | F11: 465576 | G11: 466917
A12: Feb-25 | B12: 2 | C12: Revenue | D12: Wholesale | E12: 340813 | F12: 315480 | G12: 301434
A13: Feb-25 | B13: 2 | C13: Revenue | D13: Online Sales | E13: 223658 | F13: 216492 | G13: 197162
... A217: Dec-26 | B217: 24 | C217: Expense | D217: Admin & Overheads | E217: 61480 | F217: 60838 | G217: 62486
